running/__init__.py
running/analyzeagegrade.py
running/athlinks.py
running/athlinksresults.py
running/comparegpx.py
running/competitor.py
running/competitor2csv.py
running/getweather.py
running/gpx2kml.py
running/parseralogxml.py
running/parseresults.py
running/parserun-bk3.py
running/parsetcx.py
running/ra2membersfile.py
running/racewx-render.py
running/racewx.py
running/renderclubagstats.py
running/runningahead.py
running/runningaheadmembers.py
running/runningaheadparticipants.py
running/runningaheadresults.py
running/runsignup.py
running/strava.py
running/textnormalize.py
running/ultrasignup.py
running/ultrasignupresults.py
running/version.py
running/xmldict.py
running/xmldict1.py
running/xmldict2.py
running/xmlreader.py
runtilities-2.3.0.data/scripts/analyzeagegrade.py
runtilities-2.3.0.data/scripts/athlinksresults.py
runtilities-2.3.0.data/scripts/competitor2csv.py
runtilities-2.3.0.data/scripts/parseralogxml.py
runtilities-2.3.0.data/scripts/parseresults.py
runtilities-2.3.0.data/scripts/parsetcx.py
runtilities-2.3.0.data/scripts/renderclubagstats.py
runtilities-2.3.0.data/scripts/runningaheadresults.py
runtilities-2.3.0.data/scripts/ultrasignupresults.py
runtilities-2.3.0.dist-info/METADATA
runtilities-2.3.0.dist-info/WHEEL
runtilities-2.3.0.dist-info/entry_points.txt
runtilities-2.3.0.dist-info/top_level.txt
runtilities-2.3.0.dist-info/RECORD
