Metadata-Version: 2.4
Name: runtilities
Version: 2.3.0
Summary: running related scripts
Home-page: http://github.com/louking/running
Author: Lou King
Author-email: lking@pobox.com
Classifier: Programming Language :: Python :: 3 :: Only
Classifier: Programming Language :: Python :: 3.6
Classifier: License :: OSI Approved :: Apache Software License
Classifier: Operating System :: OS Independent
Requires-Python: >=3.6
Requires-Dist: requests>=2.22.0
Requires-Dist: requests_oauthlib>=1.3.0
Requires-Dist: loutilities>=3.3.0
Requires-Dist: tzlocal>=2.0.0
Requires-Dist: xlrd>=1.2.0
Requires-Dist: unicodecsv>=0.14.1
Requires-Dist: sqlalchemy>=1.3.12
Dynamic: author
Dynamic: author-email
Dynamic: classifier
Dynamic: description
Dynamic: description-content-type
Dynamic: home-page
Dynamic: requires-dist
Dynamic: requires-python
Dynamic: summary
